herald/__init__.py
herald/decorators.py
herald/types.py
herald/utils.py
herald/messengers/__init__.py
herald/messengers/desktop.py
herald/messengers/discord.py
herald/messengers/email.py
herald_of_completion-0.3.0.dist-info/LICENSE
herald_of_completion-0.3.0.dist-info/METADATA
herald_of_completion-0.3.0.dist-info/WHEEL
herald_of_completion-0.3.0.dist-info/top_level.txt
herald_of_completion-0.3.0.dist-info/RECORD
